caustic/parser/__init__.py
caustic/parser/actions.py
caustic/parser/cli.py
caustic/parser/error.py
caustic.parser-3.0.0.dist-info/LICENSE
caustic.parser-3.0.0.dist-info/METADATA
caustic.parser-3.0.0.dist-info/WHEEL
caustic.parser-3.0.0.dist-info/entry_points.txt
caustic.parser-3.0.0.dist-info/top_level.txt
caustic.parser-3.0.0.dist-info/RECORD
