Metadata-Version: 2.1
Name: caustic.parser
Version: 3.0.0
Summary: Caustic's parsing framework
Author: Shae.c32
Project-URL: Homepage, https://codeberg.org/Caustic/CausticParser
Project-URL: Issues, https://codeberg.org/Caustic/CausticParser/issues
Keywords: caustic,language,parser,syntax,grammar
Classifier: Development Status :: 5 - Production/Stable
Classifier: Intended Audience :: Developers
Classifier: License :: OSI Approved :: Apache Software License
Classifier: Natural Language :: English
Classifier: Programming Language :: Other
Classifier: Topic :: File Formats
Classifier: Topic :: Software Development
Classifier: Topic :: Software Development :: Compilers
Classifier: Topic :: Software Development :: Interpreters
Requires-Python: >=3.9
License-File: LICENSE
Requires-Dist: parglare
Provides-Extra: cli
Requires-Dist: click ; extra == 'cli'
Provides-Extra: cst
Requires-Dist: caustic.cst ; extra == 'cst'
